<?xml version='1.0' encoding='utf-8'?>
<q:quakeml xmlns="http://quakeml.org/xmlns/bed/1.2" xmlns:q="http://quakeml.org/xmlns/quakeml/1.2">
  <eventParameters publicID="smi:local/0253f83d-62d5-44c6-b084-d33748708c8c">
    <event publicID="smi:ISC/evid=614590499">
      <preferredOriginID>smi:ISC/origid=614955782</preferredOriginID>
      <type>earthquake</type>
      <description>
        <text>Near east coast of eastern Honshu</text>
        <type>Flinn-Engdahl region</type>
      </description>
      <origin publicID="smi:ISC/origid=614955782">
        <time>
          <value>2019-01-26T08:23:02.400000Z</value>
          <uncertainty>0.3</uncertainty>
        </time>
        <latitude>
          <value>40.3151</value>
        </latitude>
        <longitude>
          <value>142.2179</value>
        </longitude>
        <depth>
          <value>47294.2</value>
        </depth>
        <quality>
          <usedPhaseCount>1073</usedPhaseCount>
          <associatedStationCount>1336</associatedStationCount>
          <standardError>1.3391</standardError>
          <azimuthalGap>85.239</azimuthalGap>
          <minimumDistance>0.404</minimumDistance>
          <maximumDistance>158.586</maximumDistance>
        </quality>
        <creationInfo>
          <author>ISC</author>
        </creationInfo>
        <originUncertainty>
          <preferredDescription>uncertainty ellipse</preferredDescription>
          <minHorizontalUncertainty>3734.54</minHorizontalUncertainty>
          <maxHorizontalUncertainty>4774.447</maxHorizontalUncertainty>
          <azimuthMaxHorizontalUncertainty>128.2</azimuthMaxHorizontalUncertainty>
        </originUncertainty>
      </origin>
      <origin publicID="smi:ISC/origid=612311457">
        <time>
          <value>2019-01-26T08:22:58.200000Z</value>
        </time>
        <latitude>
          <value>40.22</value>
        </latitude>
        <longitude>
          <value>142.56</value>
        </longitude>
        <depth>
          <value>46000.0</value>
        </depth>
        <quality>
          <usedPhaseCount>96</usedPhaseCount>
          <standardError>1.52</standardError>
          <azimuthalGap>282.0</azimuthalGap>
          <minimumDistance>9.6</minimumDistance>
          <maximumDistance>50.4</maximumDistance>
        </quality>
        <creationInfo>
          <author>BJI</author>
        </creationInfo>
      </origin>
      <origin publicID="smi:ISC/origid=611428297">
        <time>
          <value>2019-01-26T08:23:01.610000Z</value>
        </time>
        <latitude>
          <value>40.2807</value>
        </latitude>
        <longitude>
          <value>142.3275</value>
        </longitude>
        <depth>
          <value>37650.0</value>
        </depth>
        <creationInfo>
          <author>NIED</author>
        </creationInfo>
      </origin>
      <origin publicID="smi:ISC/origid=614794282">
        <time>
          <value>2019-01-26T08:23:01.610000Z</value>
          <uncertainty>0.11</uncertainty>
        </time>
        <latitude>
          <value>40.2807</value>
        </latitude>
        <longitude>
          <value>142.3275</value>
        </longitude>
        <depth>
          <value>37650.0</value>
        </depth>
        <quality>
          <associatedStationCount>40</associatedStationCount>
        </quality>
        <creationInfo>
          <author>JMA</author>
        </creationInfo>
      </origin>
      <origin publicID="smi:ISC/origid=614196238">
        <time>
          <value>2019-01-26T08:23:01.900000Z</value>
          <uncertainty>0.83</uncertainty>
        </time>
        <latitude>
          <value>40.381</value>
        </latitude>
        <longitude>
          <value>142.188</value>
        </longitude>
        <depth>
          <value>58000.0</value>
        </depth>
        <quality>
          <usedPhaseCount>201</usedPhaseCount>
        </quality>
        <creationInfo>
          <author>MOS</author>
        </creationInfo>
        <originUncertainty>
          <preferredDescription>uncertainty ellipse</preferredDescription>
          <minHorizontalUncertainty>4400.0</minHorizontalUncertainty>
          <maxHorizontalUncertainty>6100.0</maxHorizontalUncertainty>
          <azimuthMaxHorizontalUncertainty>113.0</azimuthMaxHorizontalUncertainty>
        </originUncertainty>
      </origin>
      <origin publicID="smi:ISC/origid=611870187">
        <time>
          <value>2019-01-26T08:23:02.000000Z</value>
        </time>
        <latitude>
          <value>40.3168</value>
        </latitude>
        <longitude>
          <value>142.2554</value>
        </longitude>
        <depth>
          <value>60500.0</value>
        </depth>
        <creationInfo>
          <author>NEIC</author>
        </creationInfo>
      </origin>
      <origin publicID="smi:ISC/origid=611870188">
        <time>
          <value>2019-01-26T08:23:02.000000Z</value>
        </time>
        <latitude>
          <value>40.3168</value>
        </latitude>
        <longitude>
          <value>142.78</value>
        </longitude>
        <depth>
          <value>60500.0</value>
        </depth>
        <type>centroid</type>
        <creationInfo>
          <author>NEIC</author>
        </creationInfo>
      </origin>
      <origin publicID="smi:ISC/origid=618849849">
        <time>
          <value>2019-01-26T08:23:02.840000Z</value>
        </time>
        <latitude>
          <value>40.334</value>
        </latitude>
        <longitude>
          <value>142.15</value>
        </longitude>
        <depth>
          <value>50200.0</value>
        </depth>
        <quality>
          <usedPhaseCount>914</usedPhaseCount>
          <associatedStationCount>850</associatedStationCount>
          <standardError>0.85</standardError>
        </quality>
        <creationInfo>
          <author>ISC-EHB</author>
        </creationInfo>
        <originUncertainty>
          <preferredDescription>uncertainty ellipse</preferredDescription>
          <minHorizontalUncertainty>1600.0</minHorizontalUncertainty>
          <maxHorizontalUncertainty>2400.0</maxHorizontalUncertainty>
          <azimuthMaxHorizontalUncertainty>145.0</azimuthMaxHorizontalUncertainty>
        </originUncertainty>
      </origin>
      <origin publicID="smi:ISC/origid=615250277">
        <time>
          <value>2019-01-26T08:23:03.000000Z</value>
        </time>
        <latitude>
          <value>40.333</value>
        </latitude>
        <longitude>
          <value>142.222</value>
        </longitude>
        <depth>
          <value>40750.0</value>
        </depth>
        <timeFixed>true</timeFixed>
        <epicenterFixed>true</epicenterFixed>
        <creationInfo>
          <author>ISC-PPSM</author>
        </creationInfo>
      </origin>
      <origin publicID="smi:ISC/origid=611870186">
        <time>
          <value>2019-01-26T08:23:03.140000Z</value>
          <uncertainty>1.36</uncertainty>
        </time>
        <latitude>
          <value>40.3332</value>
        </latitude>
        <longitude>
          <value>142.2224</value>
        </longitude>
        <depth>
          <value>48240.0</value>
        </depth>
        <quality>
          <usedPhaseCount>229</usedPhaseCount>
          <standardError>0.67</standardError>
          <azimuthalGap>90.0</azimuthalGap>
          <minimumDistance>0.992</minimumDistance>
        </quality>
        <creationInfo>
          <author>NEIC</author>
        </creationInfo>
        <originUncertainty>
          <preferredDescription>uncertainty ellipse</preferredDescription>
          <minHorizontalUncertainty>7003.0</minHorizontalUncertainty>
          <maxHorizontalUncertainty>12266.0</maxHorizontalUncertainty>
          <azimuthMaxHorizontalUncertainty>112.0</azimuthMaxHorizontalUncertainty>
        </originUncertainty>
      </origin>
      <origin publicID="smi:ISC/origid=613334019">
        <time>
          <value>2019-01-26T08:23:03.150000Z</value>
          <uncertainty>0.46</uncertainty>
        </time>
        <latitude>
          <value>40.235</value>
        </latitude>
        <longitude>
          <value>142.2057</value>
        </longitude>
        <depth>
          <value>56500.0</value>
        </depth>
        <quality>
          <usedPhaseCount>82</usedPhaseCount>
          <standardError>0.63</standardError>
          <azimuthalGap>97.0</azimuthalGap>
          <minimumDistance>3.89</minimumDistance>
          <maximumDistance>158.64</maximumDistance>
        </quality>
        <creationInfo>
          <author>IDC</author>
        </creationInfo>
        <originUncertainty>
          <preferredDescription>uncertainty ellipse</preferredDescription>
          <minHorizontalUncertainty>7800.0</minHorizontalUncertainty>
          <maxHorizontalUncertainty>9800.0</maxHorizontalUncertainty>
          <azimuthMaxHorizontalUncertainty>163.0</azimuthMaxHorizontalUncertainty>
        </originUncertainty>
      </origin>
      <origin publicID="smi:ISC/origid=618863313">
        <time>
          <value>2019-01-26T08:23:04.270000Z</value>
          <uncertainty>0.38</uncertainty>
        </time>
        <latitude>
          <value>40.374</value>
        </latitude>
        <longitude>
          <value>142.212</value>
        </longitude>
        <depth>
          <value>58600.0</value>
        </depth>
        <quality>
          <usedPhaseCount>53</usedPhaseCount>
          <associatedStationCount>55</associatedStationCount>
          <standardError>1.08</standardError>
          <azimuthalGap>159.2</azimuthalGap>
          <minimumDistance>0.97</minimumDistance>
          <maximumDistance>58.07</maximumDistance>
        </quality>
        <creationInfo>
          <author>GFZ</author>
        </creationInfo>
      </origin>
      <origin publicID="smi:ISC/origid=615075908">
        <time>
          <value>2019-01-26T08:23:04.730000Z</value>
        </time>
        <latitude>
          <value>41.224</value>
        </latitude>
        <longitude>
          <value>143.229</value>
        </longitude>
        <depth>
          <value>33000.0</value>
        </depth>
        <quality>
          <minimumDistance>76.93</minimumDistance>
          <maximumDistance>82.32</maximumDistance>
        </quality>
        <creationInfo>
          <author>BGR</author>
        </creationInfo>
      </origin>
      <origin publicID="smi:ISC/origid=612071154">
        <time>
          <value>2019-01-26T08:23:05.100000Z</value>
          <uncertainty>0.2</uncertainty>
        </time>
        <latitude>
          <value>40.33</value>
        </latitude>
        <longitude>
          <value>142.37</value>
        </longitude>
        <depth>
          <value>49100.0</value>
        </depth>
        <quality>
          <usedPhaseCount>331</usedPhaseCount>
          <associatedStationCount>133</associatedStationCount>
        </quality>
        <type>centroid</type>
        <creationInfo>
          <author>GCMT</author>
        </creationInfo>
      </origin>
      <magnitude publicID="smi:ISC/magid=621891156">
        <mag>
          <value>5.65</value>
          <uncertainty>0.14</uncertainty>
        </mag>
        <type>mb</type>
        <originID>smi:ISC/origid=614955782</originID>
        <stationCount>346</stationCount>
        <creationInfo>
          <author>ISC</author>
        </creationInfo>
      </magnitude>
      <magnitude publicID="smi:ISC/magid=621891155">
        <mag>
          <value>5.43</value>
          <uncertainty>0.06</uncertainty>
        </mag>
        <type>MS</type>
        <originID>smi:ISC/origid=614955782</originID>
        <stationCount>319</stationCount>
        <creationInfo>
          <author>ISC</author>
        </creationInfo>
      </magnitude>
      <magnitude publicID="smi:ISC/magid=617473866">
        <mag>
          <value>5.5</value>
        </mag>
        <type>mb</type>
        <originID>smi:ISC/origid=612311457</originID>
        <stationCount>90</stationCount>
        <creationInfo>
          <author>BJI</author>
        </creationInfo>
      </magnitude>
      <magnitude publicID="smi:ISC/magid=617473865">
        <mag>
          <value>5.7</value>
        </mag>
        <type>mB</type>
        <originID>smi:ISC/origid=612311457</originID>
        <stationCount>49</stationCount>
        <creationInfo>
          <author>BJI</author>
        </creationInfo>
      </magnitude>
      <magnitude publicID="smi:ISC/magid=617473864">
        <mag>
          <value>5.2</value>
        </mag>
        <type>Ms</type>
        <originID>smi:ISC/origid=612311457</originID>
        <stationCount>62</stationCount>
        <creationInfo>
          <author>BJI</author>
        </creationInfo>
      </magnitude>
      <magnitude publicID="smi:ISC/magid=617473867">
        <mag>
          <value>5.1</value>
        </mag>
        <type>Ms7</type>
        <originID>smi:ISC/origid=612311457</originID>
        <stationCount>61</stationCount>
        <creationInfo>
          <author>BJI</author>
        </creationInfo>
      </magnitude>
      <magnitude publicID="smi:ISC/magid=616292416">
        <mag>
          <value>5.5</value>
        </mag>
        <type>MW</type>
        <originID>smi:ISC/origid=611428297</originID>
        <creationInfo>
          <author>NIED</author>
        </creationInfo>
      </magnitude>
      <magnitude publicID="smi:ISC/magid=621471494">
        <mag>
          <value>5.6</value>
        </mag>
        <type>MD</type>
        <originID>smi:ISC/origid=614794282</originID>
        <stationCount>40</stationCount>
        <creationInfo>
          <author>JMA</author>
        </creationInfo>
      </magnitude>
      <magnitude publicID="smi:ISC/magid=621471495">
        <mag>
          <value>5.6</value>
        </mag>
        <type>MW</type>
        <originID>smi:ISC/origid=614794282</originID>
        <stationCount>40</stationCount>
        <creationInfo>
          <author>JMA</author>
        </creationInfo>
      </magnitude>
      <magnitude publicID="smi:ISC/magid=620675451">
        <mag>
          <value>5.9</value>
        </mag>
        <type>mb</type>
        <originID>smi:ISC/origid=614196238</originID>
        <stationCount>85</stationCount>
        <creationInfo>
          <author>MOS</author>
        </creationInfo>
      </magnitude>
      <magnitude publicID="smi:ISC/magid=620675450">
        <mag>
          <value>5.2</value>
        </mag>
        <type>MS</type>
        <originID>smi:ISC/origid=614196238</originID>
        <stationCount>41</stationCount>
        <creationInfo>
          <author>MOS</author>
        </creationInfo>
      </magnitude>
      <magnitude publicID="smi:ISC/magid=616893161">
        <mag>
          <value>5.5</value>
          <uncertainty>0.06</uncertainty>
        </mag>
        <type>Mww</type>
        <originID>smi:ISC/origid=611870188</originID>
        <stationCount>25</stationCount>
        <creationInfo>
          <author>NEIC</author>
        </creationInfo>
      </magnitude>
      <magnitude publicID="smi:ISC/magid=622052916">
        <mag>
          <value>6.23</value>
        </mag>
        <type>Mwppsm</type>
        <originID>smi:ISC/origid=615250277</originID>
        <creationInfo>
          <author>ISC-PPSM</author>
        </creationInfo>
      </magnitude>
      <magnitude publicID="smi:ISC/magid=616893160">
        <mag>
          <value>5.6</value>
          <uncertainty>0.04</uncertainty>
        </mag>
        <type>mb</type>
        <originID>smi:ISC/origid=611870186</originID>
        <stationCount>200</stationCount>
        <creationInfo>
          <author>NEIC</author>
        </creationInfo>
      </magnitude>
      <magnitude publicID="smi:ISC/magid=616893159">
        <mag>
          <value>5.4</value>
          <uncertainty>0.02</uncertainty>
        </mag>
        <type>Ms_20</type>
        <originID>smi:ISC/origid=611870186</originID>
        <stationCount>543</stationCount>
        <creationInfo>
          <author>NEIC</author>
        </creationInfo>
      </magnitude>
      <magnitude publicID="smi:ISC/magid=619102670">
        <mag>
          <value>5.1</value>
          <uncertainty>0.1</uncertainty>
        </mag>
        <type>mb</type>
        <originID>smi:ISC/origid=613334019</originID>
        <stationCount>51</stationCount>
        <creationInfo>
          <author>IDC</author>
        </creationInfo>
      </magnitude>
      <magnitude publicID="smi:ISC/magid=619102671">
        <mag>
          <value>5.4</value>
          <uncertainty>0.1</uncertainty>
        </mag>
        <type>mbtmp</type>
        <originID>smi:ISC/origid=613334019</originID>
        <stationCount>59</stationCount>
        <creationInfo>
          <author>IDC</author>
        </creationInfo>
      </magnitude>
      <magnitude publicID="smi:ISC/magid=619102672">
        <mag>
          <value>5.1</value>
          <uncertainty>0.0</uncertainty>
        </mag>
        <type>MS</type>
        <originID>smi:ISC/origid=613334019</originID>
        <stationCount>50</stationCount>
        <creationInfo>
          <author>IDC</author>
        </creationInfo>
      </magnitude>
      <magnitude publicID="smi:ISC/magid=626475095">
        <mag>
          <value>5.58</value>
        </mag>
        <type>M</type>
        <originID>smi:ISC/origid=618863313</originID>
        <stationCount>36</stationCount>
        <creationInfo>
          <author>GFZ</author>
        </creationInfo>
      </magnitude>
      <magnitude publicID="smi:ISC/magid=626475094">
        <mag>
          <value>5.65</value>
          <uncertainty>0.21</uncertainty>
        </mag>
        <type>mb</type>
        <originID>smi:ISC/origid=618863313</originID>
        <stationCount>36</stationCount>
        <creationInfo>
          <author>GFZ</author>
        </creationInfo>
      </magnitude>
      <magnitude publicID="smi:ISC/magid=621822532">
        <mag>
          <value>5.7</value>
        </mag>
        <type>mb</type>
        <originID>smi:ISC/origid=615075908</originID>
        <creationInfo>
          <author>BGR</author>
        </creationInfo>
      </magnitude>
      <magnitude publicID="smi:ISC/magid=621822533">
        <mag>
          <value>5.3</value>
        </mag>
        <type>Ms</type>
        <originID>smi:ISC/origid=615075908</originID>
        <creationInfo>
          <author>BGR</author>
        </creationInfo>
      </magnitude>
      <magnitude publicID="smi:ISC/magid=617096983">
        <mag>
          <value>5.58</value>
        </mag>
        <type>MW</type>
        <originID>smi:ISC/origid=612071154</originID>
        <stationCount>133</stationCount>
        <creationInfo>
          <author>GCMT</author>
        </creationInfo>
      </magnitude>
      <focalMechanism publicID="smi:ISC/fault_planes;fmid=600452264">
        <nodalPlanes>
          <nodalPlane1>
            <strike>
              <value>24.0</value>
            </strike>
            <dip>
              <value>67.0</value>
            </dip>
            <rake>
              <value>101.0</value>
            </rake>
          </nodalPlane1>
          <nodalPlane2>
            <strike>
              <value>176.0</value>
            </strike>
            <dip>
              <value>25.0</value>
            </dip>
            <rake>
              <value>65.0</value>
            </rake>
          </nodalPlane2>
        </nodalPlanes>
        <principalAxes>
          <tAxis>
            <azimuth>
              <value>314.0</value>
            </azimuth>
            <plunge>
              <value>66.0</value>
            </plunge>
            <length>
              <value>2.991e+17</value>
            </length>
          </tAxis>
          <pAxis>
            <azimuth>
              <value>105.0</value>
            </azimuth>
            <plunge>
              <value>21.0</value>
            </plunge>
            <length>
              <value>-3.004e+17</value>
            </length>
          </pAxis>
          <nAxis>
            <azimuth>
              <value>199.0</value>
            </azimuth>
            <plunge>
              <value>11.0</value>
            </plunge>
            <length>
              <value>500000000000000.0</value>
            </length>
          </nAxis>
        </principalAxes>
        <methodID>smi:ISC/methodID=Best_double_couple</methodID>
        <momentTensor publicID="smi:ISC/moment_tensor;fmid=600452264">
          <derivedOriginID>smi:ISC/origid=612071154</derivedOriginID>
          <scalarMoment>
            <value>2.998e+17</value>
          </scalarMoment>
          <tensor>
            <Mrr>
              <value>2.1e+17</value>
              <uncertainty>8700000000000000.0</uncertainty>
            </Mrr>
            <Mtt>
              <value>6200000000000000.0</value>
              <uncertainty>5700000000000000.0</uncertainty>
            </Mtt>
            <Mpp>
              <value>-2.17e+17</value>
              <uncertainty>5900000000000000.0</uncertainty>
            </Mpp>
            <Mrt>
              <value>1.04e+17</value>
              <uncertainty>5100000000000000.0</uncertainty>
            </Mrt>
            <Mrp>
              <value>1.78e+17</value>
              <uncertainty>6200000000000000.0</uncertainty>
            </Mrp>
            <Mtp>
              <value>-4.17e+16</value>
              <uncertainty>4200000000000000.0</uncertainty>
            </Mtp>
          </tensor>
          <sourceTimeFunction>
            <type>unknown</type>
            <duration>1.5</duration>
          </sourceTimeFunction>
        </momentTensor>
        <creationInfo>
          <author>GCMT</author>
        </creationInfo>
      </focalMechanism>
      <focalMechanism publicID="smi:ISC/fault_planes;fmid=600450715">
        <nodalPlanes>
          <nodalPlane1>
            <strike>
              <value>18.83</value>
            </strike>
            <dip>
              <value>53.5</value>
            </dip>
            <rake>
              <value>110.07</value>
            </rake>
          </nodalPlane1>
          <nodalPlane2>
            <strike>
              <value>167.27</value>
            </strike>
            <dip>
              <value>40.97</value>
            </dip>
            <rake>
              <value>65.12</value>
            </rake>
          </nodalPlane2>
        </nodalPlanes>
        <principalAxes>
          <tAxis>
            <azimuth>
              <value>343.0</value>
            </azimuth>
            <plunge>
              <value>73.0</value>
            </plunge>
            <length>
              <value>2.004e+17</value>
            </length>
          </tAxis>
          <pAxis>
            <azimuth>
              <value>95.0</value>
            </azimuth>
            <plunge>
              <value>7.0</value>
            </plunge>
            <length>
              <value>-2.066e+17</value>
            </length>
          </pAxis>
          <nAxis>
            <azimuth>
              <value>187.0</value>
            </azimuth>
            <plunge>
              <value>16.0</value>
            </plunge>
            <length>
              <value>6190000000000000.0</value>
            </length>
          </nAxis>
        </principalAxes>
        <momentTensor publicID="smi:ISC/moment_tensor;fmid=600450715">
          <derivedOriginID>smi:ISC/origid=611870188</derivedOriginID>
          <scalarMoment>
            <value>2.03e+17</value>
          </scalarMoment>
          <tensor>
            <Mrr>
              <value>1.804e+17</value>
            </Mrr>
            <Mtt>
              <value>2.062e+16</value>
            </Mtt>
            <Mpp>
              <value>-2.01e+17</value>
            </Mpp>
            <Mrt>
              <value>5.49e+16</value>
            </Mrt>
            <Mrp>
              <value>3.979e+16</value>
            </Mrp>
            <Mtp>
              <value>-1.237e+16</value>
            </Mtp>
          </tensor>
          <clvd>0.0599</clvd>
          <sourceTimeFunction>
            <type>unknown</type>
            <duration>2.74</duration>
          </sourceTimeFunction>
        </momentTensor>
        <creationInfo>
          <author>NEIC</author>
        </creationInfo>
      </focalMechanism>
      <focalMechanism publicID="smi:ISC/fault_planes;fmid=600680460">
        <triggeringOriginID>smi:ISC/origid=615250277</triggeringOriginID>
        <nodalPlanes>
          <nodalPlane1>
            <strike>
              <value>43.9</value>
            </strike>
            <dip>
              <value>74.0</value>
            </dip>
            <rake>
              <value>171.8</value>
            </rake>
          </nodalPlane1>
          <nodalPlane2>
            <strike>
              <value>136.2</value>
            </strike>
            <dip>
              <value>82.1</value>
            </dip>
            <rake>
              <value>16.2</value>
            </rake>
          </nodalPlane2>
        </nodalPlanes>
        <momentTensor publicID="smi:ISC/moment_tensor;fmid=600680460">
          <scalarMoment>
            <value>2.75e+18</value>
          </scalarMoment>
          <tensor>
            <Mrr>
              <value>6e+16</value>
              <uncertainty>1.22e+17</uncertainty>
            </Mrr>
            <Mtt>
              <value>6.87e+17</value>
              <uncertainty>2.18e+17</uncertainty>
            </Mtt>
            <Mpp>
              <value>-6.54e+17</value>
              <uncertainty>1.59e+17</uncertainty>
            </Mpp>
            <Mrt>
              <value>2.1e+17</value>
              <uncertainty>2.24e+17</uncertainty>
            </Mrt>
            <Mrp>
              <value>-2000000000000000.0</value>
              <uncertainty>2.78e+17</uncertainty>
            </Mrp>
            <Mtp>
              <value>-6.8e+16</value>
              <uncertainty>1.69e+17</uncertainty>
            </Mtp>
          </tensor>
        </momentTensor>
        <creationInfo>
          <author>ISC-PPSM</author>
        </creationInfo>
      </focalMechanism>
      <focalMechanism publicID="smi:ISC/fault_planes;fmid=600443834">
        <triggeringOriginID>smi:ISC/origid=611428297</triggeringOriginID>
        <nodalPlanes>
          <nodalPlane1>
            <strike>
              <value>25.0</value>
            </strike>
            <dip>
              <value>72.0</value>
            </dip>
            <rake>
              <value>100.0</value>
            </rake>
          </nodalPlane1>
          <nodalPlane2>
            <strike>
              <value>175.0</value>
            </strike>
            <dip>
              <value>20.0</value>
            </dip>
            <rake>
              <value>62.0</value>
            </rake>
          </nodalPlane2>
        </nodalPlanes>
        <momentTensor publicID="smi:ISC/moment_tensor;fmid=600443834">
          <scalarMoment>
            <value>2.13e+17</value>
          </scalarMoment>
          <tensor>
            <Mrr>
              <value>1.214e+17</value>
            </Mrr>
            <Mtt>
              <value>7340000000000000.0</value>
            </Mtt>
            <Mpp>
              <value>-1.288e+17</value>
            </Mpp>
            <Mrt>
              <value>8.163e+16</value>
            </Mrt>
            <Mrp>
              <value>1.494e+17</value>
            </Mrp>
            <Mtp>
              <value>-2.562e+16</value>
            </Mtp>
          </tensor>
          <clvd>0.03</clvd>
        </momentTensor>
        <creationInfo>
          <author>NIED</author>
        </creationInfo>
      </focalMechanism>
    </event>
  </eventParameters>
</q:quakeml>
