<?xml version='1.0' encoding='utf-8'?>
<q:quakeml xmlns="http://quakeml.org/xmlns/bed/1.2" xmlns:q="http://quakeml.org/xmlns/quakeml/1.2">
  <eventParameters publicID="smi:local/458bbd0c-b467-44df-8a4a-3dcff3db9f50">
    <event publicID="smi:ISC/evid=620213281">
      <preferredOriginID>smi:ISC/origid=615115778</preferredOriginID>
      <type>earthquake</type>
      <typeCertainty>known</typeCertainty>
      <description>
        <text>Near coast of Chiapas</text>
        <type>Flinn-Engdahl region</type>
      </description>
      <origin publicID="smi:ISC/origid=615115778">
        <time>
          <value>2019-02-01T16:14:12.400000Z</value>
          <uncertainty>0.25</uncertainty>
        </time>
        <latitude>
          <value>14.7715</value>
        </latitude>
        <longitude>
          <value>-92.2794</value>
        </longitude>
        <depth>
          <value>78141.2</value>
        </depth>
        <quality>
          <usedPhaseCount>2685</usedPhaseCount>
          <associatedStationCount>2337</associatedStationCount>
          <standardError>2.3121</standardError>
          <azimuthalGap>24.732</azimuthalGap>
          <minimumDistance>0.136</minimumDistance>
          <maximumDistance>170.771</maximumDistance>
        </quality>
        <creationInfo>
          <author>ISC</author>
        </creationInfo>
        <originUncertainty>
          <preferredDescription>uncertainty ellipse</preferredDescription>
          <minHorizontalUncertainty>3209.093</minHorizontalUncertainty>
          <maxHorizontalUncertainty>3673.804</maxHorizontalUncertainty>
          <azimuthMaxHorizontalUncertainty>47.0</azimuthMaxHorizontalUncertainty>
        </originUncertainty>
      </origin>
      <origin publicID="smi:ISC/origid=615074114">
        <time>
          <value>2019-02-01T16:14:08.700000Z</value>
          <uncertainty>2.69</uncertainty>
        </time>
        <latitude>
          <value>15.496</value>
        </latitude>
        <longitude>
          <value>-92.593</value>
        </longitude>
        <depth>
          <value>133300.0</value>
        </depth>
        <quality>
          <associatedStationCount>28</associatedStationCount>
          <standardError>0.9</standardError>
          <azimuthalGap>333.0</azimuthalGap>
        </quality>
        <creationInfo>
          <author>UPA</author>
        </creationInfo>
        <originUncertainty>
          <preferredDescription>horizontal uncertainty</preferredDescription>
          <minHorizontalUncertainty>33600.0</minHorizontalUncertainty>
          <maxHorizontalUncertainty>40000.0</maxHorizontalUncertainty>
          <azimuthMaxHorizontalUncertainty>0.0</azimuthMaxHorizontalUncertainty>
        </originUncertainty>
      </origin>
      <origin publicID="smi:ISC/origid=614961087">
        <time>
          <value>2019-02-01T16:14:11.800000Z</value>
          <uncertainty>1.28</uncertainty>
        </time>
        <latitude>
          <value>14.68</value>
        </latitude>
        <longitude>
          <value>-92.453</value>
        </longitude>
        <depth>
          <value>66000.0</value>
        </depth>
        <depthType>operator assigned</depthType>
        <epicenterFixed>true</epicenterFixed>
        <quality>
          <associatedStationCount>58</associatedStationCount>
          <standardError>0.8</standardError>
          <azimuthalGap>350.0</azimuthalGap>
        </quality>
        <creationInfo>
          <author>UCR</author>
        </creationInfo>
        <originUncertainty>
          <preferredDescription>horizontal uncertainty</preferredDescription>
          <minHorizontalUncertainty>999900.0</minHorizontalUncertainty>
          <maxHorizontalUncertainty>999900.0</maxHorizontalUncertainty>
          <azimuthMaxHorizontalUncertainty>90.0</azimuthMaxHorizontalUncertainty>
        </originUncertainty>
      </origin>
      <origin publicID="smi:ISC/origid=615305332">
        <time>
          <value>2019-02-01T16:14:12.000000Z</value>
        </time>
        <latitude>
          <value>14.68</value>
        </latitude>
        <longitude>
          <value>-92.453</value>
        </longitude>
        <depth>
          <value>43300.0</value>
        </depth>
        <timeFixed>true</timeFixed>
        <epicenterFixed>true</epicenterFixed>
        <creationInfo>
          <author>ISC-PPSM</author>
        </creationInfo>
      </origin>
      <origin publicID="smi:ISC/origid=613562674">
        <time>
          <value>2019-02-01T16:14:12.100000Z</value>
          <uncertainty>0.61</uncertainty>
        </time>
        <latitude>
          <value>14.582</value>
        </latitude>
        <longitude>
          <value>-92.481</value>
        </longitude>
        <depth>
          <value>76200.0</value>
        </depth>
        <quality>
          <associatedStationCount>21</associatedStationCount>
          <standardError>0.4</standardError>
          <azimuthalGap>194.0</azimuthalGap>
        </quality>
        <creationInfo>
          <author>MEX</author>
        </creationInfo>
        <originUncertainty>
          <preferredDescription>horizontal uncertainty</preferredDescription>
          <minHorizontalUncertainty>3900.0</minHorizontalUncertainty>
          <maxHorizontalUncertainty>4400.0</maxHorizontalUncertainty>
          <azimuthMaxHorizontalUncertainty>0.0</azimuthMaxHorizontalUncertainty>
        </originUncertainty>
      </origin>
      <origin publicID="smi:ISC/origid=618863426">
        <time>
          <value>2019-02-01T16:14:12.130000Z</value>
        </time>
        <latitude>
          <value>14.982</value>
        </latitude>
        <longitude>
          <value>-92.059</value>
        </longitude>
        <depth>
          <value>70000.0</value>
        </depth>
        <quality>
          <usedPhaseCount>286</usedPhaseCount>
          <associatedStationCount>74</associatedStationCount>
          <azimuthalGap>151.8</azimuthalGap>
          <minimumDistance>4.73</minimumDistance>
          <maximumDistance>42.86</maximumDistance>
        </quality>
        <creationInfo>
          <author>GFZ</author>
        </creationInfo>
      </origin>
      <origin publicID="smi:ISC/origid=611870844">
        <time>
          <value>2019-02-01T16:14:12.320000Z</value>
          <uncertainty>2.76</uncertainty>
        </time>
        <latitude>
          <value>14.6802</value>
        </latitude>
        <longitude>
          <value>-92.4527</value>
        </longitude>
        <depth>
          <value>66000.0</value>
        </depth>
        <depthType>operator assigned</depthType>
        <quality>
          <usedPhaseCount>100</usedPhaseCount>
          <standardError>1.36</standardError>
          <azimuthalGap>43.0</azimuthalGap>
          <minimumDistance>0.289</minimumDistance>
        </quality>
        <creationInfo>
          <author>NEIC</author>
        </creationInfo>
        <originUncertainty>
          <preferredDescription>uncertainty ellipse</preferredDescription>
          <minHorizontalUncertainty>6800.0</minHorizontalUncertainty>
          <maxHorizontalUncertainty>11100.0</maxHorizontalUncertainty>
          <azimuthMaxHorizontalUncertainty>18.0</azimuthMaxHorizontalUncertainty>
        </originUncertainty>
      </origin>
      <origin publicID="smi:ISC/origid=613334634">
        <time>
          <value>2019-02-01T16:14:12.480000Z</value>
          <uncertainty>0.62</uncertainty>
        </time>
        <latitude>
          <value>15.0365</value>
        </latitude>
        <longitude>
          <value>-91.8857</value>
        </longitude>
        <depth>
          <value>72700.0</value>
        </depth>
        <quality>
          <usedPhaseCount>79</usedPhaseCount>
          <standardError>0.97</standardError>
          <azimuthalGap>61.0</azimuthalGap>
          <minimumDistance>3.53</minimumDistance>
          <maximumDistance>156.65</maximumDistance>
        </quality>
        <creationInfo>
          <author>IDC</author>
        </creationInfo>
        <originUncertainty>
          <preferredDescription>uncertainty ellipse</preferredDescription>
          <minHorizontalUncertainty>7100.0</minHorizontalUncertainty>
          <maxHorizontalUncertainty>14000.0</maxHorizontalUncertainty>
          <azimuthMaxHorizontalUncertainty>49.0</azimuthMaxHorizontalUncertainty>
        </originUncertainty>
      </origin>
      <origin publicID="smi:ISC/origid=611422427">
        <time>
          <value>2019-02-01T16:14:13.000000Z</value>
        </time>
        <latitude>
          <value>14.763</value>
        </latitude>
        <longitude>
          <value>-92.298</value>
        </longitude>
        <depth>
          <value>75000.0</value>
        </depth>
        <creationInfo>
          <author>IPGP</author>
        </creationInfo>
      </origin>
      <origin publicID="smi:ISC/origid=611870846">
        <time>
          <value>2019-02-01T16:14:13.100000Z</value>
        </time>
        <latitude>
          <value>14.8919</value>
        </latitude>
        <longitude>
          <value>-92.2479</value>
        </longitude>
        <depth>
          <value>35500.0</value>
        </depth>
        <creationInfo>
          <author>NEIC</author>
        </creationInfo>
      </origin>
      <origin publicID="smi:ISC/origid=611870847">
        <time>
          <value>2019-02-01T16:14:13.100000Z</value>
        </time>
        <latitude>
          <value>14.9919</value>
        </latitude>
        <longitude>
          <value>-92.0</value>
        </longitude>
        <depth>
          <value>35500.0</value>
        </depth>
        <type>centroid</type>
        <creationInfo>
          <author>NEIC</author>
        </creationInfo>
      </origin>
      <origin publicID="smi:ISC/origid=615260534">
        <time>
          <value>2019-02-01T16:14:13.200000Z</value>
          <uncertainty>1.9</uncertainty>
        </time>
        <latitude>
          <value>14.8</value>
        </latitude>
        <longitude>
          <value>-92.4</value>
        </longitude>
        <depth>
          <value>87000.0</value>
        </depth>
        <quality>
          <standardError>1.33</standardError>
          <azimuthalGap>351.0</azimuthalGap>
        </quality>
        <creationInfo>
          <author>RSNC</author>
        </creationInfo>
      </origin>
      <origin publicID="smi:ISC/origid=615108433">
        <time>
          <value>2019-02-01T16:14:13.710000Z</value>
          <uncertainty>0.29</uncertainty>
        </time>
        <latitude>
          <value>14.7112</value>
        </latitude>
        <longitude>
          <value>-92.4401</value>
        </longitude>
        <depth>
          <value>48382.1</value>
        </depth>
        <quality>
          <usedPhaseCount>70</usedPhaseCount>
          <associatedStationCount>56</associatedStationCount>
          <standardError>0.9334</standardError>
          <azimuthalGap>171.933</azimuthalGap>
          <minimumDistance>0.745</minimumDistance>
          <maximumDistance>28.181</maximumDistance>
        </quality>
        <creationInfo>
          <author>CATAC</author>
        </creationInfo>
        <originUncertainty>
          <preferredDescription>uncertainty ellipse</preferredDescription>
          <minHorizontalUncertainty>3605.5</minHorizontalUncertainty>
          <maxHorizontalUncertainty>7540.82</maxHorizontalUncertainty>
          <azimuthMaxHorizontalUncertainty>36.5</azimuthMaxHorizontalUncertainty>
        </originUncertainty>
      </origin>
      <origin publicID="smi:ISC/origid=611870848">
        <time>
          <value>2019-02-01T16:14:13.800000Z</value>
        </time>
        <latitude>
          <value>14.8839</value>
        </latitude>
        <longitude>
          <value>-92.1604</value>
        </longitude>
        <depth>
          <value>74400.0</value>
        </depth>
        <creationInfo>
          <author>NEIC</author>
        </creationInfo>
      </origin>
      <origin publicID="smi:ISC/origid=612311510">
        <time>
          <value>2019-02-01T16:14:13.900000Z</value>
        </time>
        <latitude>
          <value>15.0</value>
        </latitude>
        <longitude>
          <value>-92.11</value>
        </longitude>
        <depth>
          <value>80000.0</value>
        </depth>
        <quality>
          <usedPhaseCount>89</usedPhaseCount>
          <standardError>1.57</standardError>
          <azimuthalGap>311.0</azimuthalGap>
          <minimumDistance>106.3</minimumDistance>
          <maximumDistance>139.9</maximumDistance>
        </quality>
        <creationInfo>
          <author>BJI</author>
        </creationInfo>
      </origin>
      <origin publicID="smi:ISC/origid=618849965">
        <time>
          <value>2019-02-01T16:14:14.350000Z</value>
        </time>
        <latitude>
          <value>14.87</value>
        </latitude>
        <longitude>
          <value>-92.127</value>
        </longitude>
        <depth>
          <value>93100.0</value>
        </depth>
        <quality>
          <usedPhaseCount>1857</usedPhaseCount>
          <associatedStationCount>999</associatedStationCount>
          <standardError>1.17</standardError>
        </quality>
        <creationInfo>
          <author>ISC-EHB</author>
        </creationInfo>
        <originUncertainty>
          <preferredDescription>uncertainty ellipse</preferredDescription>
          <minHorizontalUncertainty>1500.0</minHorizontalUncertainty>
          <maxHorizontalUncertainty>2700.0</maxHorizontalUncertainty>
          <azimuthMaxHorizontalUncertainty>43.0</azimuthMaxHorizontalUncertainty>
        </originUncertainty>
      </origin>
      <origin publicID="smi:ISC/origid=614196293">
        <time>
          <value>2019-02-01T16:14:14.900000Z</value>
          <uncertainty>1.19</uncertainty>
        </time>
        <latitude>
          <value>15.005</value>
        </latitude>
        <longitude>
          <value>-91.97</value>
        </longitude>
        <depth>
          <value>103000.0</value>
        </depth>
        <quality>
          <usedPhaseCount>163</usedPhaseCount>
        </quality>
        <creationInfo>
          <author>MOS</author>
        </creationInfo>
        <originUncertainty>
          <preferredDescription>uncertainty ellipse</preferredDescription>
          <minHorizontalUncertainty>4900.0</minHorizontalUncertainty>
          <maxHorizontalUncertainty>7200.0</maxHorizontalUncertainty>
          <azimuthMaxHorizontalUncertainty>93.6</azimuthMaxHorizontalUncertainty>
        </originUncertainty>
      </origin>
      <origin publicID="smi:ISC/origid=612252239">
        <time>
          <value>2019-02-01T16:14:15.200000Z</value>
        </time>
        <latitude>
          <value>14.86</value>
        </latitude>
        <longitude>
          <value>-92.46</value>
        </longitude>
        <depth>
          <value>45700.0</value>
        </depth>
        <epicenterFixed>true</epicenterFixed>
        <quality>
          <usedPhaseCount>1147</usedPhaseCount>
          <associatedStationCount>170</associatedStationCount>
        </quality>
        <type>centroid</type>
        <creationInfo>
          <author>GCMT</author>
        </creationInfo>
      </origin>
      <origin publicID="smi:ISC/origid=614370859">
        <time>
          <value>2019-02-01T16:14:15.400000Z</value>
          <uncertainty>3.07</uncertainty>
        </time>
        <latitude>
          <value>14.849</value>
        </latitude>
        <longitude>
          <value>-92.181</value>
        </longitude>
        <depth>
          <value>86000.0</value>
        </depth>
        <depthType>operator assigned</depthType>
        <epicenterFixed>true</epicenterFixed>
        <quality>
          <associatedStationCount>29</associatedStationCount>
          <standardError>1.3</standardError>
          <azimuthalGap>290.0</azimuthalGap>
        </quality>
        <creationInfo>
          <author>SNET</author>
        </creationInfo>
        <originUncertainty>
          <preferredDescription>horizontal uncertainty</preferredDescription>
          <minHorizontalUncertainty>16600.0</minHorizontalUncertainty>
          <maxHorizontalUncertainty>18300.0</maxHorizontalUncertainty>
          <azimuthMaxHorizontalUncertainty>90.0</azimuthMaxHorizontalUncertainty>
        </originUncertainty>
      </origin>
      <origin publicID="smi:ISC/origid=615075921">
        <time>
          <value>2019-02-01T16:14:22.460000Z</value>
        </time>
        <latitude>
          <value>15.61</value>
        </latitude>
        <longitude>
          <value>-90.37</value>
        </longitude>
        <depth>
          <value>97400.0</value>
        </depth>
        <quality>
          <minimumDistance>82.41</minimumDistance>
          <maximumDistance>87.36</maximumDistance>
        </quality>
        <creationInfo>
          <author>BGR</author>
        </creationInfo>
      </origin>
      <magnitude publicID="smi:ISC/magid=622049991">
        <mag>
          <value>6.09</value>
          <uncertainty>0.14</uncertainty>
        </mag>
        <type>mb</type>
        <originID>smi:ISC/origid=615115778</originID>
        <stationCount>527</stationCount>
        <creationInfo>
          <author>ISC</author>
        </creationInfo>
      </magnitude>
      <magnitude publicID="smi:ISC/magid=621820602">
        <mag>
          <value>6.3</value>
        </mag>
        <type>MW</type>
        <originID>smi:ISC/origid=615074114</originID>
        <creationInfo>
          <author>UPA</author>
        </creationInfo>
      </magnitude>
      <magnitude publicID="smi:ISC/magid=622127325">
        <mag>
          <value>6.67</value>
        </mag>
        <type>Mwppsm</type>
        <originID>smi:ISC/origid=615305332</originID>
        <creationInfo>
          <author>ISC-PPSM</author>
        </creationInfo>
      </magnitude>
      <magnitude publicID="smi:ISC/magid=626475267">
        <mag>
          <value>6.52</value>
        </mag>
        <type>Mw</type>
        <originID>smi:ISC/origid=618863426</originID>
        <stationCount>73</stationCount>
        <creationInfo>
          <author>GFZ</author>
        </creationInfo>
      </magnitude>
      <magnitude publicID="smi:ISC/magid=616893789">
        <mag>
          <value>6.2</value>
          <uncertainty>0.02</uncertainty>
        </mag>
        <type>mb</type>
        <originID>smi:ISC/origid=611870844</originID>
        <stationCount>872</stationCount>
        <creationInfo>
          <author>NEIC</author>
        </creationInfo>
      </magnitude>
      <magnitude publicID="smi:ISC/magid=616893791">
        <mag>
          <value>6.5</value>
          <uncertainty>0.03</uncertainty>
        </mag>
        <type>Mwb</type>
        <originID>smi:ISC/origid=611870844</originID>
        <stationCount>86</stationCount>
        <creationInfo>
          <author>NEIC</author>
        </creationInfo>
      </magnitude>
      <magnitude publicID="smi:ISC/magid=616893792">
        <mag>
          <value>6.5</value>
        </mag>
        <type>Md</type>
        <originID>smi:ISC/origid=611870844</originID>
        <stationCount>201</stationCount>
        <creationInfo>
          <author>MEX</author>
        </creationInfo>
      </magnitude>
      <magnitude publicID="smi:ISC/magid=619104453">
        <mag>
          <value>5.1</value>
          <uncertainty>0.1</uncertainty>
        </mag>
        <type>mb</type>
        <originID>smi:ISC/origid=613334634</originID>
        <stationCount>31</stationCount>
        <creationInfo>
          <author>IDC</author>
        </creationInfo>
      </magnitude>
      <magnitude publicID="smi:ISC/magid=619104454">
        <mag>
          <value>5.5</value>
          <uncertainty>0.1</uncertainty>
        </mag>
        <type>mbtmp</type>
        <originID>smi:ISC/origid=613334634</originID>
        <stationCount>34</stationCount>
        <creationInfo>
          <author>IDC</author>
        </creationInfo>
      </magnitude>
      <magnitude publicID="smi:ISC/magid=619104455">
        <mag>
          <value>6.1</value>
          <uncertainty>0.0</uncertainty>
        </mag>
        <type>MS</type>
        <originID>smi:ISC/origid=613334634</originID>
        <stationCount>59</stationCount>
        <creationInfo>
          <author>IDC</author>
        </creationInfo>
      </magnitude>
      <magnitude publicID="smi:ISC/magid=616282962">
        <mag>
          <value>6.6</value>
        </mag>
        <type>Mw</type>
        <originID>smi:ISC/origid=611422427</originID>
        <creationInfo>
          <author>IPGP</author>
        </creationInfo>
      </magnitude>
      <magnitude publicID="smi:ISC/magid=616893790">
        <mag>
          <value>6.7</value>
          <uncertainty>0.07</uncertainty>
        </mag>
        <type>Mww</type>
        <originID>smi:ISC/origid=611870847</originID>
        <stationCount>23</stationCount>
        <creationInfo>
          <author>NEIC</author>
        </creationInfo>
      </magnitude>
      <magnitude publicID="smi:ISC/magid=622069699">
        <mag>
          <value>6.08</value>
          <uncertainty>0.22</uncertainty>
        </mag>
        <type>mb</type>
        <originID>smi:ISC/origid=615260534</originID>
        <creationInfo>
          <author>RSNC</author>
        </creationInfo>
      </magnitude>
      <magnitude publicID="smi:ISC/magid=622069698">
        <mag>
          <value>6.48</value>
          <uncertainty>0.1</uncertainty>
        </mag>
        <type>mB</type>
        <originID>smi:ISC/origid=615260534</originID>
        <creationInfo>
          <author>RSNC</author>
        </creationInfo>
      </magnitude>
      <magnitude publicID="smi:ISC/magid=622069703">
        <mag>
          <value>6.14</value>
          <uncertainty>0.08</uncertainty>
        </mag>
        <type>Mwp</type>
        <originID>smi:ISC/origid=615260534</originID>
        <creationInfo>
          <author>RSNC</author>
        </creationInfo>
      </magnitude>
      <magnitude publicID="smi:ISC/magid=621864728">
        <mag>
          <value>6.3</value>
        </mag>
        <type>M</type>
        <originID>smi:ISC/origid=615108433</originID>
        <stationCount>33</stationCount>
        <creationInfo>
          <author>CATAC</author>
        </creationInfo>
      </magnitude>
      <magnitude publicID="smi:ISC/magid=621864723">
        <mag>
          <value>6.55</value>
          <uncertainty>0.4</uncertainty>
        </mag>
        <type>mb</type>
        <originID>smi:ISC/origid=615108433</originID>
        <stationCount>24</stationCount>
        <creationInfo>
          <author>CATAC</author>
        </creationInfo>
      </magnitude>
      <magnitude publicID="smi:ISC/magid=621864724">
        <mag>
          <value>6.62</value>
          <uncertainty>0.22</uncertainty>
        </mag>
        <type>mB</type>
        <originID>smi:ISC/origid=615108433</originID>
        <stationCount>24</stationCount>
        <creationInfo>
          <author>CATAC</author>
        </creationInfo>
      </magnitude>
      <magnitude publicID="smi:ISC/magid=621864722">
        <mag>
          <value>6.9</value>
          <uncertainty>0.35</uncertainty>
        </mag>
        <type>MLv</type>
        <originID>smi:ISC/origid=615108433</originID>
        <stationCount>33</stationCount>
        <creationInfo>
          <author>CATAC</author>
        </creationInfo>
      </magnitude>
      <magnitude publicID="smi:ISC/magid=621864725">
        <mag>
          <value>6.42</value>
          <uncertainty>0.4</uncertainty>
        </mag>
        <type>Mw(mB)</type>
        <originID>smi:ISC/origid=615108433</originID>
        <stationCount>24</stationCount>
        <creationInfo>
          <author>CATAC</author>
        </creationInfo>
      </magnitude>
      <magnitude publicID="smi:ISC/magid=621864727">
        <mag>
          <value>5.63</value>
          <uncertainty>0.43</uncertainty>
        </mag>
        <type>MwMwp</type>
        <originID>smi:ISC/origid=615108433</originID>
        <stationCount>12</stationCount>
        <creationInfo>
          <author>CATAC</author>
        </creationInfo>
      </magnitude>
      <magnitude publicID="smi:ISC/magid=621864726">
        <mag>
          <value>5.76</value>
          <uncertainty>0.43</uncertainty>
        </mag>
        <type>Mwp</type>
        <originID>smi:ISC/origid=615108433</originID>
        <stationCount>12</stationCount>
        <creationInfo>
          <author>CATAC</author>
        </creationInfo>
      </magnitude>
      <magnitude publicID="smi:ISC/magid=617474036">
        <mag>
          <value>6.2</value>
        </mag>
        <type>mB</type>
        <originID>smi:ISC/origid=612311510</originID>
        <stationCount>61</stationCount>
        <creationInfo>
          <author>BJI</author>
        </creationInfo>
      </magnitude>
      <magnitude publicID="smi:ISC/magid=617474035">
        <mag>
          <value>6.6</value>
        </mag>
        <type>Ms</type>
        <originID>smi:ISC/origid=612311510</originID>
        <stationCount>86</stationCount>
        <creationInfo>
          <author>BJI</author>
        </creationInfo>
      </magnitude>
      <magnitude publicID="smi:ISC/magid=617474037">
        <mag>
          <value>6.6</value>
        </mag>
        <type>Ms7</type>
        <originID>smi:ISC/origid=612311510</originID>
        <stationCount>82</stationCount>
        <creationInfo>
          <author>BJI</author>
        </creationInfo>
      </magnitude>
      <magnitude publicID="smi:ISC/magid=620675516">
        <mag>
          <value>5.8</value>
        </mag>
        <type>mb</type>
        <originID>smi:ISC/origid=614196293</originID>
        <stationCount>35</stationCount>
        <creationInfo>
          <author>MOS</author>
        </creationInfo>
      </magnitude>
      <magnitude publicID="smi:ISC/magid=620675515">
        <mag>
          <value>6.4</value>
        </mag>
        <type>MS</type>
        <originID>smi:ISC/origid=614196293</originID>
        <stationCount>30</stationCount>
        <creationInfo>
          <author>MOS</author>
        </creationInfo>
      </magnitude>
      <magnitude publicID="smi:ISC/magid=617413425">
        <mag>
          <value>6.65</value>
        </mag>
        <type>MW</type>
        <originID>smi:ISC/origid=612252239</originID>
        <stationCount>170</stationCount>
        <creationInfo>
          <author>GCMT</author>
        </creationInfo>
      </magnitude>
      <magnitude publicID="smi:ISC/magid=620861274">
        <mag>
          <value>6.4</value>
        </mag>
        <type>ML</type>
        <originID>smi:ISC/origid=614370859</originID>
        <creationInfo>
          <author>SNET</author>
        </creationInfo>
      </magnitude>
      <magnitude publicID="smi:ISC/magid=621822538">
        <mag>
          <value>5.8</value>
        </mag>
        <type>mb</type>
        <originID>smi:ISC/origid=615075921</originID>
        <creationInfo>
          <author>BGR</author>
        </creationInfo>
      </magnitude>
      <focalMechanism publicID="smi:ISC/fault_planes;fmid=600856599">
        <triggeringOriginID>smi:ISC/origid=618863426</triggeringOriginID>
        <nodalPlanes>
          <nodalPlane1>
            <strike>
              <value>128.96</value>
            </strike>
            <dip>
              <value>83.7</value>
            </dip>
            <rake>
              <value>99.65</value>
            </rake>
          </nodalPlane1>
          <nodalPlane2>
            <strike>
              <value>251.79</value>
            </strike>
            <dip>
              <value>11.51</value>
            </dip>
            <rake>
              <value>33.36</value>
            </rake>
          </nodalPlane2>
        </nodalPlanes>
        <principalAxes>
          <tAxis>
            <azimuth>
              <value>49.6822</value>
            </azimuth>
            <plunge>
              <value>50.3955</value>
            </plunge>
            <length>
              <value>7.332e+18</value>
            </length>
          </tAxis>
          <pAxis>
            <azimuth>
              <value>210.3126</value>
            </azimuth>
            <plunge>
              <value>37.9746</value>
            </plunge>
            <length>
              <value>-7.585e+18</value>
            </length>
          </pAxis>
          <nAxis>
            <azimuth>
              <value>307.8943</value>
            </azimuth>
            <plunge>
              <value>9.594</value>
            </plunge>
            <length>
              <value>2.527e+17</value>
            </length>
          </nAxis>
        </principalAxes>
        <momentTensor publicID="smi:ISC/moment_tensor;fmid=600856599">
          <scalarMoment>
            <value>7.462e+18</value>
          </scalarMoment>
          <tensor>
            <Mrr>
              <value>1.488e+18</value>
            </Mrr>
            <Mtt>
              <value>-2.172e+18</value>
            </Mtt>
            <Mpp>
              <value>6.846e+17</value>
            </Mpp>
            <Mrt>
              <value>5.532e+18</value>
            </Mrt>
            <Mrp>
              <value>-4.57e+18</value>
            </Mrp>
            <Mtp>
              <value>7.027e+17</value>
            </Mtp>
          </tensor>
          <clvd>0.06662448863</clvd>
        </momentTensor>
        <creationInfo>
          <author>GFZ</author>
        </creationInfo>
      </focalMechanism>
      <focalMechanism publicID="smi:ISC/fault_planes;fmid=600450749">
        <triggeringOriginID>smi:ISC/origid=611870844</triggeringOriginID>
        <nodalPlanes>
          <nodalPlane1>
            <strike>
              <value>196.4</value>
            </strike>
            <dip>
              <value>7.39</value>
            </dip>
            <rake>
              <value>-23.21</value>
            </rake>
          </nodalPlane1>
          <nodalPlane2>
            <strike>
              <value>309.44</value>
            </strike>
            <dip>
              <value>87.1</value>
            </dip>
            <rake>
              <value>-96.8</value>
            </rake>
          </nodalPlane2>
        </nodalPlanes>
        <principalAxes>
          <tAxis>
            <azimuth>
              <value>46.0</value>
            </azimuth>
            <plunge>
              <value>42.0</value>
            </plunge>
            <length>
              <value>7.051e+18</value>
            </length>
          </tAxis>
          <pAxis>
            <azimuth>
              <value>212.0</value>
            </azimuth>
            <plunge>
              <value>47.0</value>
            </plunge>
            <length>
              <value>-7.289e+18</value>
            </length>
          </pAxis>
          <nAxis>
            <azimuth>
              <value>310.0</value>
            </azimuth>
            <plunge>
              <value>7.0</value>
            </plunge>
            <length>
              <value>2.381e+17</value>
            </length>
          </nAxis>
        </principalAxes>
        <momentTensor publicID="smi:ISC/moment_tensor;fmid=600450749">
          <scalarMoment>
            <value>7.17e+18</value>
          </scalarMoment>
          <tensor>
            <Mrr>
              <value>-8.347e+17</value>
            </Mrr>
            <Mtt>
              <value>-3.764e+17</value>
            </Mtt>
            <Mpp>
              <value>1.211e+18</value>
            </Mpp>
            <Mrt>
              <value>5.524e+18</value>
            </Mrt>
            <Mrp>
              <value>-4.434e+18</value>
            </Mrp>
            <Mtp>
              <value>-3.439e+17</value>
            </Mtp>
          </tensor>
          <clvd>0.0653</clvd>
        </momentTensor>
        <creationInfo>
          <author>NEIC</author>
        </creationInfo>
      </focalMechanism>
      <focalMechanism publicID="smi:ISC/fault_planes;fmid=600450748">
        <nodalPlanes>
          <nodalPlane1>
            <strike>
              <value>211.86</value>
            </strike>
            <dip>
              <value>4.4</value>
            </dip>
            <rake>
              <value>-7.23</value>
            </rake>
          </nodalPlane1>
          <nodalPlane2>
            <strike>
              <value>309.07</value>
            </strike>
            <dip>
              <value>89.45</value>
            </dip>
            <rake>
              <value>-94.36</value>
            </rake>
          </nodalPlane2>
        </nodalPlanes>
        <principalAxes>
          <tAxis>
            <azimuth>
              <value>43.0</value>
            </azimuth>
            <plunge>
              <value>44.0</value>
            </plunge>
            <length>
              <value>1.428e+19</value>
            </length>
          </tAxis>
          <pAxis>
            <azimuth>
              <value>215.0</value>
            </azimuth>
            <plunge>
              <value>45.0</value>
            </plunge>
            <length>
              <value>-1.458e+19</value>
            </length>
          </pAxis>
          <nAxis>
            <azimuth>
              <value>309.0</value>
            </azimuth>
            <plunge>
              <value>4.0</value>
            </plunge>
            <length>
              <value>3.04e+17</value>
            </length>
          </nAxis>
        </principalAxes>
        <momentTensor publicID="smi:ISC/moment_tensor;fmid=600450748">
          <derivedOriginID>smi:ISC/origid=611870847</derivedOriginID>
          <scalarMoment>
            <value>1.44e+19</value>
          </scalarMoment>
          <tensor>
            <Mrr>
              <value>-4.27e+17</value>
            </Mrr>
            <Mtt>
              <value>-8.78e+17</value>
            </Mtt>
            <Mpp>
              <value>1.305e+18</value>
            </Mpp>
            <Mrt>
              <value>1.12e+19</value>
            </Mrt>
            <Mrp>
              <value>-9.033e+18</value>
            </Mrp>
            <Mtp>
              <value>-1.39e+17</value>
            </Mtp>
          </tensor>
          <clvd>0.0417</clvd>
          <sourceTimeFunction>
            <type>unknown</type>
            <duration>9.32</duration>
          </sourceTimeFunction>
        </momentTensor>
        <creationInfo>
          <author>NEIC</author>
        </creationInfo>
      </focalMechanism>
      <focalMechanism publicID="smi:ISC/fault_planes;fmid=600682140">
        <triggeringOriginID>smi:ISC/origid=615305332</triggeringOriginID>
        <nodalPlanes>
          <nodalPlane1>
            <strike>
              <value>117.0</value>
            </strike>
            <dip>
              <value>68.9</value>
            </dip>
            <rake>
              <value>78.9</value>
            </rake>
          </nodalPlane1>
          <nodalPlane2>
            <strike>
              <value>325.5</value>
            </strike>
            <dip>
              <value>23.7</value>
            </dip>
            <rake>
              <value>116.4</value>
            </rake>
          </nodalPlane2>
        </nodalPlanes>
        <momentTensor publicID="smi:ISC/moment_tensor;fmid=600682140">
          <scalarMoment>
            <value>1.26e+19</value>
          </scalarMoment>
          <tensor>
            <Mrr>
              <value>2.28e+18</value>
              <uncertainty>1.68e+18</uncertainty>
            </Mrr>
            <Mtt>
              <value>-4.33e+18</value>
              <uncertainty>1.64e+18</uncertainty>
            </Mtt>
            <Mpp>
              <value>-2.96e+18</value>
              <uncertainty>1.51e+18</uncertainty>
            </Mpp>
            <Mrt>
              <value>4.41e+18</value>
              <uncertainty>9.6e+17</uncertainty>
            </Mrt>
            <Mrp>
              <value>3.17e+18</value>
              <uncertainty>1.67e+18</uncertainty>
            </Mrp>
            <Mtp>
              <value>-2.04e+18</value>
              <uncertainty>1.05e+18</uncertainty>
            </Mtp>
          </tensor>
        </momentTensor>
        <creationInfo>
          <author>ISC-PPSM</author>
        </creationInfo>
      </focalMechanism>
      <focalMechanism publicID="smi:ISC/fault_planes;fmid=600452774">
        <nodalPlanes>
          <nodalPlane1>
            <strike>
              <value>202.0</value>
            </strike>
            <dip>
              <value>8.0</value>
            </dip>
            <rake>
              <value>-17.0</value>
            </rake>
          </nodalPlane1>
          <nodalPlane2>
            <strike>
              <value>310.0</value>
            </strike>
            <dip>
              <value>88.0</value>
            </dip>
            <rake>
              <value>-97.0</value>
            </rake>
          </nodalPlane2>
        </nodalPlanes>
        <principalAxes>
          <tAxis>
            <azimuth>
              <value>47.0</value>
            </azimuth>
            <plunge>
              <value>42.0</value>
            </plunge>
            <length>
              <value>1.217e+19</value>
            </length>
          </tAxis>
          <pAxis>
            <azimuth>
              <value>212.0</value>
            </azimuth>
            <plunge>
              <value>47.0</value>
            </plunge>
            <length>
              <value>-1.197e+19</value>
            </length>
          </pAxis>
          <nAxis>
            <azimuth>
              <value>310.0</value>
            </azimuth>
            <plunge>
              <value>7.0</value>
            </plunge>
            <length>
              <value>-2.1e+17</value>
            </length>
          </nAxis>
        </principalAxes>
        <methodID>smi:ISC/methodID=Best_double_couple</methodID>
        <momentTensor publicID="smi:ISC/moment_tensor;fmid=600452774">
          <derivedOriginID>smi:ISC/origid=612252239</derivedOriginID>
          <scalarMoment>
            <value>1.207e+19</value>
          </scalarMoment>
          <tensor>
            <Mrr>
              <value>-8.4e+17</value>
              <uncertainty>3e+16</uncertainty>
            </Mrr>
            <Mtt>
              <value>-9.5e+17</value>
              <uncertainty>2e+16</uncertainty>
            </Mtt>
            <Mpp>
              <value>1.7e+18</value>
              <uncertainty>3e+16</uncertainty>
            </Mpp>
            <Mrt>
              <value>9.21e+18</value>
              <uncertainty>9e+16</uncertainty>
            </Mrt>
            <Mrp>
              <value>-7.6e+18</value>
              <uncertainty>8e+16</uncertainty>
            </Mrp>
            <Mtp>
              <value>-8.9e+17</value>
              <uncertainty>2e+16</uncertainty>
            </Mtp>
          </tensor>
          <sourceTimeFunction>
            <type>unknown</type>
            <duration>5.2</duration>
          </sourceTimeFunction>
        </momentTensor>
        <creationInfo>
          <author>GCMT</author>
        </creationInfo>
      </focalMechanism>
      <focalMechanism publicID="smi:ISC/fault_planes;fmid=600443727">
        <triggeringOriginID>smi:ISC/origid=611422427</triggeringOriginID>
        <nodalPlanes>
          <nodalPlane1>
            <strike>
              <value>211.0</value>
            </strike>
            <dip>
              <value>10.0</value>
            </dip>
            <rake>
              <value>-9.0</value>
            </rake>
          </nodalPlane1>
          <nodalPlane2>
            <strike>
              <value>310.0</value>
            </strike>
            <dip>
              <value>88.0</value>
            </dip>
            <rake>
              <value>-100.0</value>
            </rake>
          </nodalPlane2>
        </nodalPlanes>
        <creationInfo>
          <author>IPGP</author>
        </creationInfo>
      </focalMechanism>
    </event>
  </eventParameters>
</q:quakeml>
